async_temp_email/__init__.py
async_temp_email/_app/__init__.py
async_temp_email/_app/_emailnator/__init__.py
async_temp_email/_app/_emailnator/_client.py
async_temp_email/_app/_emailnator/_config.py
async_temp_email/_app/_emailnator/_http_clients.py
async_temp_email/_app/_emailnator/_polling.py
async_temp_email/_app/_emailnator/_schemas.py
async_temp_email/_app/_emailnator/_service.py
async_temp_email/_app/_emailnator/_tokens_provider.py
async_temp_email/_core/__init__.py
async_temp_email/_core/_base_client.py
async_temp_email/_core/_interfaces.py
async_temp_email/_core/_schemas.py
async_temp_email/_core/_types.py
async_temp_email-0.1.0.dist-info/licenses/LICENSE
async_temp_email-0.1.0.dist-info/METADATA
async_temp_email-0.1.0.dist-info/WHEEL
async_temp_email-0.1.0.dist-info/RECORD
