Metadata-Version: 2.4
Name: async-temp-email
Version: 0.1.0
Summary: Asynchronous Python library for working with temporary email services
License: MIT
License-File: LICENSE
Keywords: temporary-email,async,email,email-api,temp-mail
Author: lionex-ui
Author-email: eugenemescaline@gmail.com
Requires-Python: >=3.12
Classifier: Development Status :: 4 - Beta
Classifier: Intended Audience :: Developers
Classifier: License :: OSI Approved :: MIT License
Classifier: Operating System :: OS Independent
Classifier: Programming Language :: Python :: 3
Classifier: Programming Language :: Python :: 3.12
Classifier: Programming Language :: Python :: 3.13
Classifier: Topic :: Software Development :: Libraries :: Python Modules
Classifier: Topic :: Communications :: Email
Classifier: Typing :: Typed
Classifier: Framework :: AsyncIO
Requires-Dist: bs4 (>=0.0.2,<0.0.3)
Requires-Dist: dateparser (>=1.2.2,<2.0.0)
Requires-Dist: httpx[http2] (>=0.28.1,<0.29.0)
Requires-Dist: pydantic[email] (>=2.12.5,<3.0.0)
